tvb/__init__.py
tvb/storage/__init__.py
tvb/storage/storage_interface.py
tvb/storage/h5/__init__.py
tvb/storage/h5/decorators.py
tvb/storage/h5/utils.py
tvb/storage/h5/encryption/__init__.py
tvb/storage/h5/encryption/data_encryption_handler.py
tvb/storage/h5/encryption/encryption_handler.py
tvb/storage/h5/encryption/import_export_encryption_handler.py
tvb/storage/h5/file/__init__.py
tvb/storage/h5/file/exceptions.py
tvb/storage/h5/file/files_helper.py
tvb/storage/h5/file/hdf5_storage_manager.py
tvb/storage/h5/file/xml_metadata_handlers.py
tvb/storage/kube/__init__.py
tvb/storage/kube/kube_notifier.py
tvb/tests/storage/__init__.py
tvb/tests/storage/files_helper_test.py
tvb/tests/storage/hdf5_storage_test.py
tvb/tests/storage/storage_test.py
tvb/tests/storage/test_read.xml
tvb/tests/storage/xml_metadata_handlers_test.py
tvb/tests/storage/dummy/__init__.py
tvb/tests/storage/dummy/dummy_project.py
tvb/tests/storage/dummy/dummy_storage_data_h5.py
tvb_storage-2.9.dist-info/AUTHORS
tvb_storage-2.9.dist-info/LICENSE
tvb_storage-2.9.dist-info/METADATA
tvb_storage-2.9.dist-info/WHEEL
tvb_storage-2.9.dist-info/top_level.txt
tvb_storage-2.9.dist-info/RECORD
